jvc_projector/__init__.py
jvc_projector/commands.py
jvc_projector/jvc_projector.py
jvc_projector/optimal_settings.py
mock/__init__.py
mock/mochrie.py
tests/__init__.py
tests/testSuite.py
jvc_projector_remote_improved-2.2.1.dist-info/LICENSE
jvc_projector_remote_improved-2.2.1.dist-info/METADATA
jvc_projector_remote_improved-2.2.1.dist-info/WHEEL
jvc_projector_remote_improved-2.2.1.dist-info/top_level.txt
jvc_projector_remote_improved-2.2.1.dist-info/RECORD
