Metadata-Version: 2.1
Name: jvc-projector-remote-improved
Version: 2.2.1
Summary: A package to control JVC projectors over IP
Home-page: https://github.com/iloveicedgreentea/jvc_projector_improved
Author: iloveicedgreentea
Classifier: Programming Language :: Python :: 3.9
Classifier: License :: OSI Approved :: MIT License
Classifier: Operating System :: OS Independent
License-File: LICENSE
